beautify/__init__.py
pybeautify-2.0.dist-info/LICENSE
pybeautify-2.0.dist-info/METADATA
pybeautify-2.0.dist-info/WHEEL
pybeautify-2.0.dist-info/top_level.txt
pybeautify-2.0.dist-info/RECORD
