Metadata-Version: 2.1
Name: pybeautify
Version: 2.0
Summary: Beautify
Home-page: https://github.com/CKVB/Beautifier
Author: Chaitanya Krishna VB
Author-email: python7460@gmail.com
License: MIT LICENSE
Platform: UNKNOWN
Classifier: Programming Language :: Python :: 3
Classifier: License :: OSI Approved :: MIT License
Classifier: Operating System :: OS Independent
